autolook_api/__init__.py
autolook_api/alapi.py
autolook_api/client.py
autolook_api/error.py
autolook_api/logger.py
autolook_api-0.2.0.dist-info/METADATA
autolook_api-0.2.0.dist-info/WHEEL
autolook_api-0.2.0.dist-info/RECORD
