Metadata-Version: 2.4
Name: autolook_api
Version: 0.2.0
Summary: Official API wrapper client for the autolook.al service
Project-URL: Homepage, https://autolook.al
Project-URL: GitHub, https://github.com/AutolookOrg/autolook-api-py
Author-email: Autolook <autolook.al@proton.me>
Classifier: Operating System :: OS Independent
Classifier: Programming Language :: Python :: 3
Requires-Python: >=3.10
Requires-Dist: aiohttp>=3
Requires-Dist: backports-zstd>=1
Requires-Dist: brotli>=1
Requires-Dist: colorama>=0.4
Requires-Dist: colorlog>=6
Requires-Dist: python-dotenv>=1
Requires-Dist: typing-extensions>=4
